pathetic.py
pathetic_cli-0.3.0.dist-info/METADATA
pathetic_cli-0.3.0.dist-info/WHEEL
pathetic_cli-0.3.0.dist-info/entry_points.txt
pathetic_cli-0.3.0.dist-info/licenses/LICENSE
pathetic_cli-0.3.0.dist-info/RECORD
