Metadata-Version: 2.4
Name: pathetic-cli
Version: 0.3.0
Summary: A colorful CLI that visualizes system, environment, and PATH info with Rich.
Project-URL: Homepage, https://github.com/lancereinsmith/pathetic
Project-URL: Repository, https://github.com/lancereinsmith/pathetic
Project-URL: Issues, https://github.com/lancereinsmith/pathetic/issues
Author-email: Lance Reinsmith <info@k2rad.com>
License: MIT License
License-File: LICENSE
Classifier: Development Status :: 3 - Alpha
Classifier: Environment :: Console
Classifier: Intended Audience :: Developers
Classifier: License :: OSI Approved :: MIT License
Classifier: Programming Language :: Python
Classifier: Programming Language :: Python :: 3
Classifier: Programming Language :: Python :: 3 :: Only
Classifier: Programming Language :: Python :: 3.14
Classifier: Topic :: System :: Systems Administration
Classifier: Topic :: Utilities
Requires-Python: >=3.12
Requires-Dist: click>=8.3.1
Requires-Dist: rich>=14.3.1
